{
    "Colbourn" : ["Charlie Colbourn", "cybersecurity"],
    "Sen"      : ["Arunabha Sen", "cybersecurity"],
    "Xue"      : ["Guoliang Xue", "big_data"],
    "Richa"    : ["Andrea Richa", "big_data"],
    "Doupe"    : ["Adam Doupe", "cybersecurity"],
    "Huang"    : ["Dijiang Huang", "cybersecurity"],
    "Sarwat"   : ["Mohammad Sarwat", "big_data"],
    "Candan"   : ["Selchuk Candan", "big_data"],
    "Rao"      : ["Subbarao Kambhampati", "ai"],
    "Liu"      : ["Huan Liu", "big_data"],
    "Zhang"    : ["Yu Zhang", "ai"],
    "Amor"     : ["Heni Ben Amor", "ai"]
}
